{
  "examples": {
    "async_cuda": {
      "example": "async",
      "metadata": {
        "best_optimization": "prefetch",
        "best_optimization_file": "optimized_async_prefetch.cu",
        "best_optimization_speedup": 1.0509415189344251,
        "best_optimization_time_ms": 225.71526933461428,
        "git_commit": "58aba661efb22d9aae526aee0d76d04b2d13e0b7",
        "updated_at": "2025-11-24T17:19:11.125294"
      },
      "metrics": {
        "baseline_p75_ms": 231.55661900091218,
        "baseline_p90_ms": 231.55661900091218,
        "baseline_time_ms": 237.2135480012124,
        "best_optimized_p75_ms": 225.18622300412972,
        "best_optimized_p90_ms": 225.18622300412972,
        "best_optimized_speedup": 1.0509415189344251,
        "best_optimized_time_ms": 225.71526933461428,
        "best_speedup": 1.0509415189344251
      },
      "type": "cuda"
    },
    "async_prefetch": {
      "example": "async_prefetch",
      "metadata": {
        "best_optimization": "optimized_async_prefetch",
        "best_optimization_file": "optimized_async_prefetch.py",
        "best_optimization_speedup": 0.00018346737835924222,
        "best_optimization_time_ms": 261.62689208984375,
        "git_commit": "8a9453873dcdbae15df8064ed77b6b20d3d8e49e",
        "updated_at": "2025-11-25T19:44:07.110004"
      },
      "metrics": {
        "baseline_p75_ms": 0.048,
        "baseline_throughput.latency_ms": 0.048,
        "baseline_throughput.requests_per_s": 20833.333333333332,
        "baseline_time_ms": 0.048,
        "best_optimized_p75_ms": 213.76007080078125,
        "best_optimized_speedup": 0.00018346737835924222,
        "best_optimized_throughput.latency_ms": 213.68878173828125,
        "best_optimized_throughput.requests_per_s": 4.6797028457243295,
        "best_optimized_time_ms": 213.68878173828125,
        "best_speedup": 1.0
      },
      "type": "python"
    },
    "hbm_cuda": {
      "example": "hbm",
      "metadata": {
        "best_optimization": "peak",
        "best_optimization_file": "optimized_hbm_peak.cu",
        "best_optimization_speedup": 5.345849709396076,
        "best_optimization_time_ms": 271.60865667004447,
        "git_commit": "8a9453873dcdbae15df8064ed77b6b20d3d8e49e",
        "updated_at": "2025-11-25T20:29:11.412372"
      },
      "metrics": {
        "baseline_p75_ms": 1448.4829510038253,
        "baseline_p90_ms": 1448.4829510038253,
        "baseline_time_ms": 1451.979058329016,
        "best_optimized_p75_ms": 287.7667470020242,
        "best_optimized_p90_ms": 287.7667470020242,
        "best_optimized_speedup": 5.345849709396076,
        "best_optimized_time_ms": 240.10338600298078,
        "best_speedup": 5.345849709396076
      },
      "type": "cuda"
    },
    "hbmcopy": {
      "example": "hbmcopy",
      "metadata": {
        "best_optimization": "optimized_hbmcopy",
        "best_optimization_file": "optimized_hbmcopy.py",
        "best_optimization_speedup": 61.41666666666667,
        "best_optimization_time_ms": 0.12,
        "git_commit": "58aba661efb22d9aae526aee0d76d04b2d13e0b7",
        "updated_at": "2025-11-24T17:16:57.082205"
      },
      "metrics": {
        "baseline_p75_ms": 7.37,
        "baseline_throughput.latency_ms": 7.37,
        "baseline_throughput.requests_per_s": 135.68521031207598,
        "baseline_time_ms": 7.37,
        "best_optimized_p75_ms": 0.12,
        "best_optimized_speedup": 61.41666666666667,
        "best_optimized_throughput.latency_ms": 0.12,
        "best_optimized_throughput.requests_per_s": 8333.333333333334,
        "best_optimized_time_ms": 0.12,
        "best_speedup": 61.41666666666667
      },
      "type": "python"
    },
    "hbmpeak": {
      "example": "hbmpeak",
      "metadata": {
        "best_optimization": "optimized_hbmpeak",
        "best_optimization_file": "optimized_hbmpeak.py",
        "best_optimization_speedup": 269.3178294573644,
        "best_optimization_time_ms": 0.43,
        "git_commit": "58aba661efb22d9aae526aee0d76d04b2d13e0b7",
        "updated_at": "2025-11-24T17:17:13.880840"
      },
      "metrics": {
        "baseline_p75_ms": 115.72,
        "baseline_throughput.latency_ms": 115.80666666666667,
        "baseline_throughput.requests_per_s": 8.63508145760175,
        "baseline_time_ms": 115.80666666666667,
        "best_optimized_p75_ms": 0.43,
        "best_optimized_speedup": 269.3178294573644,
        "best_optimized_throughput.latency_ms": 0.43,
        "best_optimized_throughput.requests_per_s": 2325.5813953488373,
        "best_optimized_time_ms": 0.43,
        "best_speedup": 269.3178294573644
      },
      "type": "python"
    },
    "lookup": {
      "example": "lookup",
      "metadata": {
        "best_optimization": "optimized_lookup",
        "best_optimization_file": "optimized_lookup.py",
        "best_optimization_speedup": 39.74285714285714,
        "best_optimization_time_ms": 0.005833333333333334,
        "git_commit": "58aba661efb22d9aae526aee0d76d04b2d13e0b7",
        "updated_at": "2025-11-24T17:17:27.518632"
      },
      "metrics": {
        "baseline_p75_ms": 0.2318,
        "baseline_throughput.latency_ms": 0.23183333333333334,
        "baseline_throughput.requests_per_s": 4313.443565780014,
        "baseline_time_ms": 0.23183333333333334,
        "best_optimized_p75_ms": 0.0058,
        "best_optimized_speedup": 39.74285714285714,
        "best_optimized_throughput.latency_ms": 0.005833333333333334,
        "best_optimized_throughput.requests_per_s": 171428.57142857142,
        "best_optimized_time_ms": 0.005833333333333334,
        "best_speedup": 39.74285714285714
      },
      "type": "python"
    },
    "lookup_cuda": {
      "example": "lookup",
      "metadata": {
        "best_optimization": "optimized_lookup",
        "best_optimization_file": "optimized_lookup.cu",
        "best_optimization_speedup": 0.7102869236098929,
        "best_optimization_time_ms": 402.8663823313157,
        "git_commit": "93e7c34588cfab78bdfc5128a3b7c3f3e4254747",
        "updated_at": "2025-11-25T11:07:58.733088"
      },
      "metrics": {
        "baseline_p75_ms": 280.9606749942759,
        "baseline_p90_ms": 280.9606749942759,
        "baseline_time_ms": 286.1507233319571,
        "best_optimized_p75_ms": 403.28946699446533,
        "best_optimized_p90_ms": 403.28946699446533,
        "best_optimized_speedup": 0.7102869236098929,
        "best_optimized_time_ms": 402.8663823313157,
        "best_speedup": 1.0
      },
      "type": "cuda"
    },
    "matmul_cuda": {
      "example": "matmul",
      "metadata": {
        "best_optimization": "tiled",
        "best_optimization_file": "optimized_matmul_tiled.cu",
        "best_optimization_speedup": 1.6542033774795295,
        "best_optimization_time_ms": 275.28503399419907,
        "git_commit": "8a9453873dcdbae15df8064ed77b6b20d3d8e49e",
        "updated_at": "2025-11-25T20:29:13.696781"
      },
      "metrics": {
        "baseline_p75_ms": 455.1886760164052,
        "baseline_p90_ms": 432.78079299489036,
        "baseline_throughput.latency_ms": 1.0490949999999999,
        "baseline_throughput.requests_per_s": 953.2025221738737,
        "baseline_time_ms": 455.37743300277117,
        "best_optimized_p75_ms": 272.4438849836588,
        "best_optimized_p90_ms": 246.13334400055464,
        "best_optimized_speedup": 1.6542033774795295,
        "best_optimized_throughput.latency_ms": 0.2792213333333333,
        "best_optimized_throughput.requests_per_s": 4733.481333516362,
        "best_optimized_time_ms": 275.28503399419907,
        "best_speedup": 1.6542033774795295
      },
      "type": "cuda"
    },
    "memory_access": {
      "example": "memory_access",
      "metadata": {
        "best_optimization": "optimized_memory_access",
        "best_optimization_file": "optimized_memory_access.py",
        "best_optimization_speedup": 7.809492063492063,
        "best_optimization_time_ms": 0.021,
        "git_commit": "58aba661efb22d9aae526aee0d76d04b2d13e0b7",
        "updated_at": "2025-11-24T17:17:55.139702"
      },
      "metrics": {
        "baseline_p75_ms": 0.163994,
        "baseline_throughput.latency_ms": 0.16399933333333333,
        "baseline_throughput.requests_per_s": 6097.58576254375,
        "baseline_time_ms": 0.16399933333333333,
        "best_optimized_p75_ms": 0.021,
        "best_optimized_speedup": 7.809492063492063,
        "best_optimized_throughput.latency_ms": 0.021,
        "best_optimized_throughput.requests_per_s": 47619.04761904761,
        "best_optimized_time_ms": 0.021,
        "best_speedup": 7.809492063492063
      },
      "type": "python"
    },
    "memory_cuda": {
      "example": "memory",
      "metadata": {
        "best_optimization": "access",
        "best_optimization_file": "optimized_memory_access.cu",
        "best_optimization_speedup": 1.05805873401545,
        "best_optimization_time_ms": 365.037865335277,
        "git_commit": "93e7c34588cfab78bdfc5128a3b7c3f3e4254747",
        "updated_at": "2025-11-25T11:07:40.031213"
      },
      "metrics": {
        "baseline_p75_ms": 385.28179899731185,
        "baseline_p90_ms": 385.28179899731185,
        "baseline_time_ms": 386.23150166434544,
        "best_optimized_p75_ms": 483.8278240058571,
        "best_optimized_p90_ms": 483.8278240058571,
        "best_optimized_speedup": 1.0591384966462116,
        "best_optimized_time_ms": 392.5355673345621,
        "best_speedup": 1.0591384966462116
      },
      "type": "cuda"
    },
    "scalar_copy": {
      "example": "scalar_copy",
      "metadata": {
        "best_optimization": "optimized_scalar_copy",
        "best_optimization_file": "optimized_scalar_copy.py",
        "best_optimization_speedup": 0.05417634124890062,
        "best_optimization_time_ms": 0.758,
        "git_commit": "8a9453873dcdbae15df8064ed77b6b20d3d8e49e",
        "updated_at": "2025-11-25T20:27:52.048881"
      },
      "metrics": {
        "baseline_p75_ms": 0.040952,
        "baseline_throughput.latency_ms": 0.04106566666666667,
        "baseline_throughput.requests_per_s": 24351.242319212317,
        "baseline_time_ms": 0.04106566666666667,
        "best_optimized_p75_ms": 0.969,
        "best_optimized_speedup": 0.05417634124890062,
        "best_optimized_throughput.latency_ms": 0.758,
        "best_optimized_throughput.requests_per_s": 1319.2612137203166,
        "best_optimized_time_ms": 0.758,
        "best_speedup": 1.0
      },
      "type": "python"
    },
    "tma_bulk_tensor_2d": {
      "example": "tma_bulk_tensor_2d",
      "metadata": {
        "best_optimization": "optimized_tma_bulk_tensor_2d",
        "best_optimization_file": "optimized_tma_bulk_tensor_2d.py",
        "best_optimization_speedup": 3.857142857142857,
        "best_optimization_time_ms": 0.007,
        "git_commit": "58aba661efb22d9aae526aee0d76d04b2d13e0b7",
        "updated_at": "2025-11-24T17:18:22.387457"
      },
      "metrics": {
        "baseline_p75_ms": 0.027,
        "baseline_throughput.latency_ms": 0.027,
        "baseline_throughput.requests_per_s": 37037.03703703704,
        "baseline_time_ms": 0.027,
        "best_optimized_p75_ms": 0.007,
        "best_optimized_speedup": 3.857142857142857,
        "best_optimized_throughput.latency_ms": 0.007,
        "best_optimized_throughput.requests_per_s": 142857.14285714287,
        "best_optimized_time_ms": 0.007,
        "best_speedup": 3.857142857142857
      },
      "type": "python"
    },
    "tma_copy": {
      "example": "tma_copy",
      "metadata": {
        "best_optimization": "optimized_tma_copy",
        "best_optimization_file": "optimized_tma_copy.py",
        "best_optimization_speedup": 14.226252158894646,
        "best_optimization_time_ms": 0.193,
        "git_commit": "58aba661efb22d9aae526aee0d76d04b2d13e0b7",
        "updated_at": "2025-11-24T17:18:39.336103"
      },
      "metrics": {
        "baseline_p75_ms": 2.744,
        "baseline_throughput.latency_ms": 2.7456666666666667,
        "baseline_throughput.requests_per_s": 364.2102707296346,
        "baseline_time_ms": 2.7456666666666667,
        "best_optimized_p75_ms": 0.193,
        "best_optimized_speedup": 14.226252158894646,
        "best_optimized_throughput.latency_ms": 0.193,
        "best_optimized_throughput.requests_per_s": 5181.347150259067,
        "best_optimized_time_ms": 0.193,
        "best_speedup": 14.226252158894646
      },
      "type": "python"
    },
    "tma_cuda": {
      "example": "tma",
      "metadata": {
        "best_optimization": "copy",
        "best_optimization_file": "optimized_tma_copy.cu",
        "best_optimization_speedup": 1.0937738497451754,
        "best_optimization_time_ms": 507.91918133230257,
        "git_commit": "8a9453873dcdbae15df8064ed77b6b20d3d8e49e",
        "updated_at": "2025-11-25T20:29:01.982124"
      },
      "metrics": {
        "baseline_p75_ms": 557.5941290007904,
        "baseline_p90_ms": 557.5941290007904,
        "baseline_time_ms": 555.5487183252504,
        "best_optimized_p75_ms": 508.629302988993,
        "best_optimized_p90_ms": 508.629302988993,
        "best_optimized_speedup": 0.9660267921857748,
        "best_optimized_time_ms": 507.91918133230257,
        "best_speedup": 1.0
      },
      "type": "cuda"
    },
    "transpose": {
      "example": "transpose",
      "metadata": {
        "best_optimization": "optimized_transpose",
        "best_optimization_file": "optimized_transpose.py",
        "best_optimization_speedup": 5.212121212121211,
        "best_optimization_time_ms": 0.033,
        "git_commit": "58aba661efb22d9aae526aee0d76d04b2d13e0b7",
        "updated_at": "2025-11-24T17:18:53.426204"
      },
      "metrics": {
        "baseline_p75_ms": 0.172,
        "baseline_throughput.latency_ms": 0.172,
        "baseline_throughput.requests_per_s": 5813.9534883720935,
        "baseline_time_ms": 0.172,
        "best_optimized_p75_ms": 0.033,
        "best_optimized_speedup": 5.212121212121211,
        "best_optimized_throughput.latency_ms": 0.033,
        "best_optimized_throughput.requests_per_s": 30303.0303030303,
        "best_optimized_time_ms": 0.033,
        "best_speedup": 5.212121212121211
      },
      "type": "python"
    },
    "transpose_cuda": {
      "example": "transpose",
      "metadata": {
        "best_optimization": "padded",
        "best_optimization_file": "optimized_transpose_padded.cu",
        "best_optimization_speedup": 1.1542558314652784,
        "best_optimization_time_ms": 366.6791943323915,
        "git_commit": "58aba661efb22d9aae526aee0d76d04b2d13e0b7",
        "updated_at": "2025-11-24T17:19:15.978189"
      },
      "metrics": {
        "baseline_p75_ms": 421.76086000108626,
        "baseline_p90_ms": 421.76086000108626,
        "baseline_time_ms": 423.24159833515296,
        "best_optimized_p75_ms": 371.4979240030516,
        "best_optimized_p90_ms": 371.4979240030516,
        "best_optimized_speedup": 1.1542558314652784,
        "best_optimized_time_ms": 366.6791943323915,
        "best_speedup": 1.1542558314652784
      },
      "type": "cuda"
    },
    "uncoalesced_copy": {
      "example": "uncoalesced_copy",
      "metadata": {
        "best_optimization": "optimized_uncoalesced_copy",
        "best_optimization_file": "optimized_uncoalesced_copy.py",
        "best_optimization_speedup": 231.65286075137323,
        "best_optimization_time_ms": 0.008313666666666667,
        "git_commit": "58aba661efb22d9aae526aee0d76d04b2d13e0b7",
        "updated_at": "2025-11-24T17:19:07.134777"
      },
      "metrics": {
        "baseline_p75_ms": 1.925905,
        "baseline_throughput.latency_ms": 1.9258846666666667,
        "baseline_throughput.requests_per_s": 519.2418929897844,
        "baseline_time_ms": 1.9258846666666667,
        "best_optimized_p75_ms": 0.008313,
        "best_optimized_speedup": 231.65286075137323,
        "best_optimized_throughput.latency_ms": 0.008313666666666667,
        "best_optimized_throughput.requests_per_s": 120283.86993304199,
        "best_optimized_time_ms": 0.008313666666666667,
        "best_speedup": 231.65286075137323
      },
      "type": "python"
    }
  },
  "hardware_key": "b200"
}
